praisonai_svc/__init__.py
praisonai_svc/app.py
praisonai_svc/cli.py
praisonai_svc/py.typed
praisonai_svc/worker.py
praisonai_svc/azure/__init__.py
praisonai_svc/azure/blob.py
praisonai_svc/azure/queue.py
praisonai_svc/azure/table.py
praisonai_svc/models/__init__.py
praisonai_svc/models/config.py
praisonai_svc/models/job.py
praisonai_svc-1.2.0.dist-info/METADATA
praisonai_svc-1.2.0.dist-info/WHEEL
praisonai_svc-1.2.0.dist-info/entry_points.txt
praisonai_svc-1.2.0.dist-info/licenses/LICENSE
praisonai_svc-1.2.0.dist-info/RECORD
