Metadata-Version: 2.4
Name: praisonai-svc
Version: 1.2.0
Summary: A unified framework that turns any PraisonAI Python package into a web service on Azure
Project-URL: Homepage, https://praison.ai
Project-URL: Documentation, https://mervinpraison.github.io/PraisonAI-SVC
Project-URL: Repository, https://github.com/MervinPraison/PraisonAI-SVC
Project-URL: Issues, https://github.com/MervinPraison/PraisonAI-SVC/issues
Author: MervinPraison
License-Expression: MIT
License-File: LICENSE
Keywords: azure,fastapi,microservices,praisonai,serverless
Classifier: Development Status :: 4 - Beta
Classifier: Framework :: FastAPI
Classifier: Intended Audience :: Developers
Classifier: License :: OSI Approved :: MIT License
Classifier: Programming Language :: Python :: 3
Classifier: Programming Language :: Python :: 3.11
Classifier: Programming Language :: Python :: 3.12
Classifier: Topic :: Software Development :: Libraries :: Python Modules
Requires-Python: >=3.11
Requires-Dist: azure-data-tables>=12.6.0
Requires-Dist: azure-identity>=1.19.0
Requires-Dist: azure-storage-blob>=12.23.0
Requires-Dist: azure-storage-queue>=12.12.0
Requires-Dist: click>=8.1.7
Requires-Dist: fastapi>=0.115.0
Requires-Dist: httpx>=0.27.0
Requires-Dist: pydantic-settings>=2.6.0
Requires-Dist: pydantic>=2.9.0
Requires-Dist: python-dotenv>=1.0.0
Requires-Dist: python-multipart>=0.0.12
Requires-Dist: pyyaml>=6.0.2
Requires-Dist: tenacity>=9.0.0
Requires-Dist: uvicorn[standard]>=0.32.0
Provides-Extra: dev
Requires-Dist: black>=24.10.0; extra == 'dev'
Requires-Dist: mypy>=1.13.0; extra == 'dev'
Requires-Dist: pytest-asyncio>=0.24.0; extra == 'dev'
Requires-Dist: pytest-cov>=6.0.0; extra == 'dev'
Requires-Dist: pytest>=8.3.0; extra == 'dev'
Requires-Dist: ruff>=0.7.0; extra == 'dev'
